StraitFlux/__init__.py
StraitFlux/functions.py
StraitFlux/functions_VP.py
StraitFlux/indices.py
StraitFlux/masterscript_cross.py
StraitFlux/masterscript_line.py
StraitFlux/preprocessing.py
StraitFlux-1.1.0.dist-info/LICENSE
StraitFlux-1.1.0.dist-info/METADATA
StraitFlux-1.1.0.dist-info/WHEEL
StraitFlux-1.1.0.dist-info/top_level.txt
StraitFlux-1.1.0.dist-info/RECORD
